functic/VERSION
functic/__init__.py
functic/_functic.py
functic/app.py
functic/config.py
functic/functions/__init__.py
functic/functions/azure/__init__.py
functic/functions/azure/get_weather_forecast_daily.py
functic/functions/azure/get_weather_forecast_hourly.py
functic/functions/google/__init__.py
functic/functions/google/get_maps_geocode.py
functic/types/__init__.py
functic/types/assistant_create.py
functic/types/chat_completion_tool.py
functic/types/chat_completion_tool_message.py
functic/types/pagination.py
functic/types/tool_output.py
functic/utils/__init__.py
functic/utils/display.py
functic/utils/function_definition.py
functic/utils/function_tool.py
functic/utils/get.py
functic/utils/import_.py
functic/utils/openai_utils/__init__.py
functic/utils/openai_utils/ensure.py
functic/utils/openai_utils/event_handlers.py
functic/utils/openai_utils/iter_.py
functic/utils/run.py
functic/version.py
functic-0.3.0.dist-info/LICENSE
functic-0.3.0.dist-info/METADATA
functic-0.3.0.dist-info/WHEEL
functic-0.3.0.dist-info/RECORD
